sympyhelpers/__init__.py
sympyhelpers/sympyhelpers.py
sympyhelpers-1.3.0.dist-info/licenses/LICENSE
sympyhelpers-1.3.0.dist-info/METADATA
sympyhelpers-1.3.0.dist-info/WHEEL
sympyhelpers-1.3.0.dist-info/top_level.txt
sympyhelpers-1.3.0.dist-info/RECORD
